MANIFEST.in
README.rst
setup.py
version.txt
micral_grain_core/__init__.py
micral_grain_core/micral_grain_core.py
micral_grain_core/version.txt
micral_grain_core.egg-info/PKG-INFO
micral_grain_core.egg-info/SOURCES.txt
micral_grain_core.egg-info/dependency_links.txt
micral_grain_core.egg-info/not-zip-safe
micral_grain_core.egg-info/requires.txt
micral_grain_core.egg-info/top_level.txt