Metadata-Version: 1.0
Name: micral-grain-core
Version: 2.0
Summary: Separation tool between coarse and ultrafine grain - core module
Home-page: UNKNOWN
Author: Yann LEROY
Author-email: yann.leroy102@orange.fr
License: MIT
Platform: UNKNOWN
